downloader/__init__.py
file_downloader-0.5.1.dist-info/METADATA
file_downloader-0.5.1.dist-info/RECORD
file_downloader-0.5.1.dist-info/WHEEL
file_downloader-0.5.1.dist-info/top_level.txt
