Metadata-Version: 2.1
Name: file-downloader
Version: 0.5.1
Summary: Downloads files via HTTP or FTP
Home-page: https://github.com/bantonj/downloader
Author: Joshua Banton
Author-email: bantonj@gmail.com
License: MIT
Keywords: download
Platform: UNKNOWN
Classifier: Programming Language :: Python :: 3
Classifier: License :: OSI Approved :: MIT License
Classifier: Operating System :: OS Independent
